{
  "openapi": "3.0.1",
  "info": {
    "title": "Flightly",
    "version": "1.0"
  },
  "paths": {
    "/Flights": {
      "get": {
        "tags": [
          "Flights"
        ],
        "parameters": [
          {
            "name": "FlightNumber",
            "in": "query",
            "schema": {
              "type": "string"
            }
          },
          {
            "name": "AirlineName",
            "in": "query",
            "schema": {
              "type": "string"
            }
          },
          {
            "name": "SortBy",
            "in": "query",
            "schema": {
              "type": "string"
            }
          },
          {
            "name": "IsDescending",
            "in": "query",
            "schema": {
              "type": "boolean"
            }
          },
          {
            "name": "PageNumber",
            "in": "query",
            "schema": {
              "type": "integer",
              "format": "int32"
            }
          },
          {
            "name": "PageSize",
            "in": "query",
            "schema": {
              "type": "integer",
              "format": "int32"
            }
          }
        ],
        "responses": {
          "200": {
            "description": "OK"
          }
        }
      }
    }
  },
  "components": { }
}